boundless_ai/__init__.py
boundless_ai/base.py
boundless_ai/schemas/base.py
boundless_ai-0.1.1.dist-info/METADATA
boundless_ai-0.1.1.dist-info/WHEEL
boundless_ai-0.1.1.dist-info/RECORD
