Metadata-Version: 2.1
Name: boundless-ai
Version: 0.1.1
Summary: Python SDK for Boundless AI.
License: MIT
Author: AI Bootstrapper
Author-email: aibootstrapper@gmail.com
Requires-Python: >=3.9,<4.0
Classifier: License :: OSI Approved :: MIT License
Classifier: Programming Language :: Python :: 3
Classifier: Programming Language :: Python :: 3.9
Classifier: Programming Language :: Python :: 3.10
Classifier: Programming Language :: Python :: 3.11
Requires-Dist: pydantic (>=1.10.9,<2.0.0)
Requires-Dist: ratelimiter (>=1.2.0.post0,<2.0.0)
Requires-Dist: requests (>=2.26.0,<3.0.0)
